Metadata-Version: 2.1
Name: ondc
Version: 0.0.1
Summary: python adaptor for ondc
Home-page: https://github.com/vamc-k/python-ondc
Author: Krishna
Author-email: info@vambook.in
License: UNKNOWN
Project-URL: Bug Tracker, https://github.com/vamc-k/python-ondc/issues
Keywords: ondc adaptor
Platform: UNKNOWN
Classifier: Programming Language :: Python :: 3
Classifier: License :: OSI Approved :: MIT License
Classifier: Operating System :: OS Independent
Requires-Python: >=3.6
